erc1066_x402/__init__.py
erc1066_x402/client.py
erc1066_x402/types.py
erc1066_x402/utils.py
hyperkitlabs_erc1066_x402-0.2.0.dist-info/METADATA
hyperkitlabs_erc1066_x402-0.2.0.dist-info/WHEEL
hyperkitlabs_erc1066_x402-0.2.0.dist-info/top_level.txt
hyperkitlabs_erc1066_x402-0.2.0.dist-info/RECORD
